rdsalesbilling/EcsInterface.py
rdsalesbilling/__init__.py
rdsalesbilling/mainModel.py
rdsalesbilling/metadata.py
rdsalesbilling/operation.py
rdsalesbilling/utility.py
rdsalesbilling-1.4.2.dist-info/METADATA
rdsalesbilling-1.4.2.dist-info/WHEEL
rdsalesbilling-1.4.2.dist-info/top_level.txt
rdsalesbilling-1.4.2.dist-info/RECORD
